setup.py
salure_helpers/recruitee/__init__.py
salure_helpers/recruitee/recruitee.py
salure_helpers_recruitee.egg-info/PKG-INFO
salure_helpers_recruitee.egg-info/SOURCES.txt
salure_helpers_recruitee.egg-info/dependency_links.txt
salure_helpers_recruitee.egg-info/not-zip-safe
salure_helpers_recruitee.egg-info/requires.txt
salure_helpers_recruitee.egg-info/top_level.txt